nj/__init__.py
nj-0.0.5.dist-info/licenses/LICENSE
nj-0.0.5.dist-info/METADATA
nj-0.0.5.dist-info/WHEEL
nj-0.0.5.dist-info/top_level.txt
nj-0.0.5.dist-info/RECORD
