Metadata-Version: 2.4
Name: nj
Version: 0.0.5
Summary: Triangle plots
Home-page: https://github.com/t-c-w/nj
Author: Thor Whalen
License: apache-2.0
Platform: any
License-File: LICENSE
Dynamic: license-file
